ctx_vector.py
layers.py
neuron.py
runner.py
shapes.py
shaping_network.py
type_defs.py
shaping_network-0.1.1.dist-info/licenses/LICENSE
shaping_network-0.1.1.dist-info/METADATA
shaping_network-0.1.1.dist-info/WHEEL
shaping_network-0.1.1.dist-info/top_level.txt
shaping_network-0.1.1.dist-info/RECORD
